nrgkick_api/__init__.py
nrgkick_api/api.py
nrgkick_api/const.py
nrgkick_api/enums.py
nrgkick_api/exceptions.py
nrgkick_api/py.typed
nrgkick_api-1.5.0.dist-info/licenses/LICENSE
nrgkick_api-1.5.0.dist-info/METADATA
nrgkick_api-1.5.0.dist-info/WHEEL
nrgkick_api-1.5.0.dist-info/top_level.txt
nrgkick_api-1.5.0.dist-info/RECORD
