Metadata-Version: 2.4
Name: nrgkick-api
Version: 1.5.0
Summary: Async Python client for NRGkick Gen2 EV charger local REST API
Author-email: Andreas Jakl <andreas.jakl@live.com>
License-Expression: MIT
Project-URL: Homepage, https://github.com/andijakl/nrgkick-api
Project-URL: Documentation, https://github.com/andijakl/nrgkick-api#readme
Project-URL: Repository, https://github.com/andijakl/nrgkick-api
Project-URL: Issues, https://github.com/andijakl/nrgkick-api/issues
Keywords: nrgkick,ev,charger,home-assistant,async,api
Classifier: Development Status :: 5 - Production/Stable
Classifier: Intended Audience :: Developers
Classifier: Operating System :: OS Independent
Classifier: Programming Language :: Python :: 3
Classifier: Programming Language :: Python :: 3.11
Classifier: Programming Language :: Python :: 3.12
Classifier: Programming Language :: Python :: 3.13
Classifier: Topic :: Home Automation
Classifier: Topic :: Software Development :: Libraries :: Python Modules
Classifier: Framework :: AsyncIO
Requires-Python: >=3.11
License-File: LICENSE
Requires-Dist: aiohttp>=3.13.2
Provides-Extra: dev
Requires-Dist: pytest>=9.0.2; extra == "dev"
Requires-Dist: pytest-asyncio>=1.3.0; extra == "dev"
Requires-Dist: pytest-cov>=7.0.0; extra == "dev"
Requires-Dist: aresponses>=3.0.0; extra == "dev"
Requires-Dist: ruff>=0.14.9; extra == "dev"
Requires-Dist: mypy>=1.19.0; extra == "dev"
Requires-Dist: build>=1.3.0; extra == "dev"
Requires-Dist: twine>=6.2.0; extra == "dev"
Requires-Dist: pre-commit>=4.5.0; extra == "dev"
Dynamic: license-file
